setaset/__init__.py
setaset/setop.py
setaset-0.0.2.dist-info/LICENSE
setaset-0.0.2.dist-info/METADATA
setaset-0.0.2.dist-info/WHEEL
setaset-0.0.2.dist-info/top_level.txt
setaset-0.0.2.dist-info/RECORD
